pydwt/__init__.py
pydwt/app.py
pydwt/context/connection.py
pydwt/context/datasources.py
pydwt/core/__init__.py
pydwt/core/containers.py
pydwt/core/dag.py
pydwt/core/enums.py
pydwt/core/executors.py
pydwt/core/project.py
pydwt/core/schedule.py
pydwt/core/task.py
pydwt/core/workflow.py
pydwt/sql/dataframe.py
pydwt/sql/materializations.py
pydwt/sql/session.py
pydwt-0.1.1.dist-info/entry_points.txt
pydwt-0.1.1.dist-info/LICENSE
pydwt-0.1.1.dist-info/WHEEL
pydwt-0.1.1.dist-info/METADATA
pydwt-0.1.1.dist-info/RECORD
