Metadata-Version: 2.1
Name: pydwt
Version: 0.1.1
Summary: 
Author: gonza
Author-email: matgonzalez@hotmail.fr
Requires-Python: >=3.8,<4.0
Classifier: Programming Language :: Python :: 3
Classifier: Programming Language :: Python :: 3.8
Classifier: Programming Language :: Python :: 3.9
Classifier: Programming Language :: Python :: 3.10
Classifier: Programming Language :: Python :: 3.11
Requires-Dist: dependency-injector (>=4.41.0,<5.0.0)
Requires-Dist: matplotlib (>=3.6.3,<4.0.0)
Requires-Dist: networkx (>=3.0,<4.0)
Requires-Dist: pyyaml (>=6.0,<7.0)
Requires-Dist: sqlalchemy (>=2.0.1,<3.0.0)
Requires-Dist: typer (>=0.7.0,<0.8.0)
